cars_szalma_2021/__init__.py
cars_szalma_2021/cars_szalma.py
cars_szalma_2021-0.1.4.dist-info/LICENSE
cars_szalma_2021-0.1.4.dist-info/METADATA
cars_szalma_2021-0.1.4.dist-info/WHEEL
cars_szalma_2021-0.1.4.dist-info/top_level.txt
cars_szalma_2021-0.1.4.dist-info/RECORD
